COPYRIGHT.txt
README.rst
setup.py
src/ScreenCapLibrary/__init__.py
src/ScreenCapLibrary/client.py
src/ScreenCapLibrary/gifclient.py
src/ScreenCapLibrary/library.py
src/ScreenCapLibrary/pygtk.py
src/ScreenCapLibrary/utils.py
src/ScreenCapLibrary/version.py
src/ScreenCapLibrary/videoclient.py
src/robotframework_screencaplibrary_sf.egg-info/PKG-INFO
src/robotframework_screencaplibrary_sf.egg-info/SOURCES.txt
src/robotframework_screencaplibrary_sf.egg-info/dependency_links.txt
src/robotframework_screencaplibrary_sf.egg-info/requires.txt
src/robotframework_screencaplibrary_sf.egg-info/top_level.txt