Metadata-Version: 1.1
Name: robotframework-screencaplibrary-sf
Version: 1.6.1.dev2
Summary: Robot Framework test library for taking screenshots
Home-page: https://github.com/rticau/ScreenCapLibrary
Author: Mihai Pârvu
Author-email: mihai-catalin.parvu@nokia.com
License: Apache License 2.0
Keywords: robotframework testing testautomation screenshot screencap
Platform: any
Classifier: Development Status :: 5 - Production/Stable
Classifier: License :: OSI Approved :: Apache Software License
Classifier: Operating System :: OS Independent
Classifier: Programming Language :: Python
Classifier: Programming Language :: Python :: 2.7
Classifier: Programming Language :: Python :: 3.4
Classifier: Programming Language :: Python :: 3.5
Classifier: Programming Language :: Python :: 3.6
Classifier: Programming Language :: Python :: 3.7
Classifier: Programming Language :: Python :: 3.8
Classifier: Topic :: Software Development :: Testing
Classifier: Framework :: Robot Framework
Classifier: Framework :: Robot Framework :: Library
